{
  "web": {
    "client_id": "191355778882-102ld24r814grfl87i1kndlc1fo1bngb.apps.googleusercontent.com",
    "project_id": "catalogapp-212116",
    "auth_uri": "https://accounts.google.com/o/oauth2/auth",
    "token_uri": "https://www.googleapis.com/oauth2/v3/token",
    "auth_provider_x509_cert_url": "https://www.googleapis.com/oauth2/v1/certs",
    "client_secret": "4RavIsSVS49hB-sfVboreBUP",
    "redirect_uris": [
      "http://www.example.com/oauth2callback",
      "http://ec2-35-182-221-65.ca-central-1.compute.amazonaws.com/oauth2callback",
      "http://35.182.221.65.xip.io/oauth2callback"
    ],
    "javascript_origins": [
      "http://www.example.com",
      "http://localhost:8000",
      "http://ec2-35-182-221-65.ca-central-1.compute.amazonaws.com",
      "http://35.182.221.65.xip.io"
    ]
  }
}